{
  "Heo-100": {
    "type": "image",
    "container": [
      {
        "text": "Heo-100-亲亲",
        "icon": "<img src='https://www.ordchaos.com/img/emojis/Heo-100/kiss.png'>"
      },
      {
        "text": "Heo-100-再见",
        "icon": "<img src='https://www.ordchaos.com/img/emojis/Heo-100/bye.png'>"
      },
      {
        "text": "Heo-100-加班",
        "icon": "<img src='https://www.ordchaos.com/img/emojis/Heo-100/overtime.png'>"
      },
      {
        "text": "Heo-100-发红包",
        "icon": "<img src='https://www.ordchaos.com/img/emojis/Heo-100/send_red_packet.png'>"
      },
      {
        "text": "Heo-100-吃瓜",
        "icon": "<img src='https://www.ordchaos.com/img/emojis/Heo-100/eat_watermelon.png'>"
      },
      {
        "text": "Heo-100-吐血",
        "icon": "<img src='https://www.ordchaos.com/img/emojis/Heo-100/vomit_blood.png'>"
      },
      {
        "text": "Heo-100-吵架",
        "icon": "<img src='https://www.ordchaos.com/img/emojis/Heo-100/argue.png'>"
      },
      {
        "text": "Heo-100-呲牙笑",
        "icon": "<img src='https://www.ordchaos.com/img/emojis/Heo-100/grin.png'>"
      },
      {
        "text": "Heo-100-哈士奇",
        "icon": "<img src='https://www.ordchaos.com/img/emojis/Heo-100/husky.png'>"
      },
      {
        "text": "Heo-100-哭泣",
        "icon": "<img src='https://www.ordchaos.com/img/emojis/Heo-100/cry.png'>"
      },
      {
        "text": "Heo-100-唱歌",
        "icon": "<img src='https://www.ordchaos.com/img/emojis/Heo-100/sing.png'>"
      },
      {
        "text": "Heo-100-喜欢",
        "icon": "<img src='https://www.ordchaos.com/img/emojis/Heo-100/like.png'>"
      },
      {
        "text": "Heo-100-大笑",
        "icon": "<img src='https://www.ordchaos.com/img/emojis/Heo-100/laugh.png'>"
      },
      {
        "text": "Heo-100-头秃",
        "icon": "<img src='https://www.ordchaos.com/img/emojis/Heo-100/bald.png'>"
      },
      {
        "text": "Heo-100-奋斗",
        "icon": "<img src='https://www.ordchaos.com/img/emojis/Heo-100/struggle.png'>"
      },
      {
        "text": "Heo-100-害羞",
        "icon": "<img src='https://www.ordchaos.com/img/emojis/Heo-100/shy.png'>"
      },
      {
        "text": "Heo-100-尴尬",
        "icon": "<img src='https://www.ordchaos.com/img/emojis/Heo-100/awkward.png'>"
      },
      {
        "text": "Heo-100-开心",
        "icon": "<img src='https://www.ordchaos.com/img/emojis/Heo-100/happy.png'>"
      },
      {
        "text": "Heo-100-微笑",
        "icon": "<img src='https://www.ordchaos.com/img/emojis/Heo-100/smile.png'>"
      },
      {
        "text": "Heo-100-思考",
        "icon": "<img src='https://www.ordchaos.com/img/emojis/Heo-100/think.png'>"
      },
      {
        "text": "Heo-100-恶心",
        "icon": "<img src='https://www.ordchaos.com/img/emojis/Heo-100/nauseated.png'>"
      },
      {
        "text": "Heo-100-惊吓",
        "icon": "<img src='https://www.ordchaos.com/img/emojis/Heo-100/shock.png'>"
      },
      {
        "text": "Heo-100-惊讶",
        "icon": "<img src='https://www.ordchaos.com/img/emojis/Heo-100/surprised.png'>"
      },
      {
        "text": "Heo-100-感动",
        "icon": "<img src='https://www.ordchaos.com/img/emojis/Heo-100/touched.png'>"
      },
      {
        "text": "Heo-100-愤怒",
        "icon": "<img src='https://www.ordchaos.com/img/emojis/Heo-100/angry.png'>"
      },
      {
        "text": "Heo-100-我看好你",
        "icon": "<img src='https://www.ordchaos.com/img/emojis/Heo-100/i_got_you.png'>"
      },
      {
        "text": "Heo-100-抠鼻",
        "icon": "<img src='https://www.ordchaos.com/img/emojis/Heo-100/pick_nose.png'>"
      },
      {
        "text": "Heo-100-捂嘴笑",
        "icon": "<img src='https://www.ordchaos.com/img/emojis/Heo-100/cover_mouth_laugh.png'>"
      },
      {
        "text": "Heo-100-捂脸",
        "icon": "<img src='https://www.ordchaos.com/img/emojis/Heo-100/facepalm.png'>"
      },
      {
        "text": "Heo-100-擦汗",
        "icon": "<img src='https://www.ordchaos.com/img/emojis/Heo-100/wipe_sweat.png'>"
      },
      {
        "text": "Heo-100-滑稽",
        "icon": "<img src='https://www.ordchaos.com/img/emojis/Heo-100/funny.png'>"
      },
      {
        "text": "Heo-100-烦恼",
        "icon": "<img src='https://www.ordchaos.com/img/emojis/Heo-100/worried.png'>"
      },
      {
        "text": "Heo-100-熬夜",
        "icon": "<img src='https://www.ordchaos.com/img/emojis/Heo-100/stay_up_late.png'>"
      },
      {
        "text": "Heo-100-爆炸",
        "icon": "<img src='https://www.ordchaos.com/img/emojis/Heo-100/explode.png'>"
      },
      {
        "text": "Heo-100-牛年进宝",
        "icon": "<img src='https://www.ordchaos.com/img/emojis/Heo-100/ox_year_treasure.png'>"
      },
      {
        "text": "Heo-100-狗头",
        "icon": "<img src='https://www.ordchaos.com/img/emojis/Heo-100/dog_head.png'>"
      },
      {
        "text": "Heo-100-狗头围脖",
        "icon": "<img src='https://www.ordchaos.com/img/emojis/Heo-100/dog_head_scarf.png'>"
      },
      {
        "text": "Heo-100-狗头胖次",
        "icon": "<img src='https://www.ordchaos.com/img/emojis/Heo-100/dog_head_pantsu.png'>"
      },
      {
        "text": "Heo-100-狗头花",
        "icon": "<img src='https://www.ordchaos.com/img/emojis/Heo-100/dog_head_flower.png'>"
      },
      {
        "text": "Heo-100-狗头草",
        "icon": "<img src='https://www.ordchaos.com/img/emojis/Heo-100/dog_head_grass.png'>"
      },
      {
        "text": "Heo-100-生病",
        "icon": "<img src='https://www.ordchaos.com/img/emojis/Heo-100/sick.png'>"
      },
      {
        "text": "Heo-100-疑问",
        "icon": "<img src='https://www.ordchaos.com/img/emojis/Heo-100/question.png'>"
      },
      {
        "text": "Heo-100-眩晕",
        "icon": "<img src='https://www.ordchaos.com/img/emojis/Heo-100/dizzy.png'>"
      },
      {
        "text": "Heo-100-睡觉",
        "icon": "<img src='https://www.ordchaos.com/img/emojis/Heo-100/sleep.png'>"
      },
      {
        "text": "Heo-100-禁言",
        "icon": "<img src='https://www.ordchaos.com/img/emojis/Heo-100/muted.png'>"
      },
      {
        "text": "Heo-100-笑哭",
        "icon": "<img src='https://www.ordchaos.com/img/emojis/Heo-100/cry_laugh.png'>"
      },
      {
        "text": "Heo-100-纠结",
        "icon": "<img src='https://www.ordchaos.com/img/emojis/Heo-100/tangled.png'>"
      },
      {
        "text": "Heo-100-绿帽",
        "icon": "<img src='https://www.ordchaos.com/img/emojis/Heo-100/green_hat.png'>"
      },
      {
        "text": "Heo-100-耍酷",
        "icon": "<img src='https://www.ordchaos.com/img/emojis/Heo-100/cool.png'>"
      },
      {
        "text": "Heo-100-被打",
        "icon": "<img src='https://www.ordchaos.com/img/emojis/Heo-100/beaten.png'>"
      },
      {
        "text": "Heo-100-送福",
        "icon": "<img src='https://www.ordchaos.com/img/emojis/Heo-100/send_blessing.png'>"
      },
      {
        "text": "Heo-100-阴险",
        "icon": "<img src='https://www.ordchaos.com/img/emojis/Heo-100/sinister.png'>"
      },
      {
        "text": "Heo-100-鬼脸",
        "icon": "<img src='https://www.ordchaos.com/img/emojis/Heo-100/grimace.png'>"
      },
      {
        "text": "Heo-100-鼓掌",
        "icon": "<img src='https://www.ordchaos.com/img/emojis/Heo-100/clap.png'>"
      }
    ]
  },
  "Bilibili": {
    "type": "image",
    "container": [
      {
        "icon": "<img src='https://www.ordchaos.com/img/emojis/Bilibili/tv_doge.png'>",
        "text": "tv_doge"
      },
      {
        "icon": "<img src='https://www.ordchaos.com/img/emojis/Bilibili/tv_kiss.png'>",
        "text": "tv_亲亲"
      },
      {
        "icon": "<img src='https://www.ordchaos.com/img/emojis/Bilibili/tv_giggle.png'>",
        "text": "tv_偷笑"
      },
      {
        "icon": "<img src='https://www.ordchaos.com/img/emojis/Bilibili/tv_bye.png'>",
        "text": "tv_再见"
      },
      {
        "icon": "<img src='https://www.ordchaos.com/img/emojis/Bilibili/tv_cold.png'>",
        "text": "tv_冷漠"
      },
      {
        "icon": "<img src='https://www.ordchaos.com/img/emojis/Bilibili/tv_angry.png'>",
        "text": "tv_发怒"
      },
      {
        "icon": "<img src='https://www.ordchaos.com/img/emojis/Bilibili/tv_rich.png'>",
        "text": "tv_发财"
      },
      {
        "icon": "<img src='https://www.ordchaos.com/img/emojis/Bilibili/tv_cute.png'>",
        "text": "tv_可爱"
      },
      {
        "icon": "<img src='https://www.ordchaos.com/img/emojis/Bilibili/tv_vomit_blood.png'>",
        "text": "tv_吐血"
      },
      {
        "icon": "<img src='https://www.ordchaos.com/img/emojis/Bilibili/tv_daze.png'>",
        "text": "tv_呆"
      },
      {
        "icon": "<img src='https://www.ordchaos.com/img/emojis/Bilibili/tv_vomit.png'>",
        "text": "tv_呕吐"
      },
      {
        "icon": "<img src='https://www.ordchaos.com/img/emojis/Bilibili/tv_sleepy.png'>",
        "text": "tv_困"
      },
      {
        "icon": "<img src='https://www.ordchaos.com/img/emojis/Bilibili/tv_smirk.png'>",
        "text": "tv_坏笑"
      },
      {
        "icon": "<img src='https://www.ordchaos.com/img/emojis/Bilibili/tv_boss.png'>",
        "text": "tv_大佬"
      },
      {
        "icon": "<img src='https://www.ordchaos.com/img/emojis/Bilibili/tv_cry.png'>",
        "text": "tv_大哭"
      },
      {
        "icon": "<img src='https://www.ordchaos.com/img/emojis/Bilibili/tv_grievance.png'>",
        "text": "tv_委屈"
      },
      {
        "icon": "<img src='https://www.ordchaos.com/img/emojis/Bilibili/tv_shy.png'>",
        "text": "tv_害羞"
      },
      {
        "icon": "<img src='https://www.ordchaos.com/img/emojis/Bilibili/tv_awkward.png'>",
        "text": "tv_尴尬"
      },
      {
        "icon": "<img src='https://www.ordchaos.com/img/emojis/Bilibili/tv_smile.png'>",
        "text": "tv_微笑"
      },
      {
        "icon": "<img src='https://www.ordchaos.com/img/emojis/Bilibili/tv_think.png'>",
        "text": "tv_思考"
      },
      {
        "icon": "<img src='https://www.ordchaos.com/img/emojis/Bilibili/tv_shock.png'>",
        "text": "tv_惊吓"
      }
    ]
  }
}
